{
  "id": "2011-09-19-votanos-en-los-premios-bitacoras-2011",
  "published_at": "2011-09-19 12:00:38 +0200",
  "title": "Vótanos en los premios Bitacoras 2011",
  "content": "Hola amigos.\r\n\r\nHace algunos días <a href=\"http://blogs.lainformacion.com/premiosbitacoras/2011/09/14/video-completo-de-la-presentacion-de-los-premios/\">arrancó la séptima edición</a> de los <a href=\"http://bitacoras.com/premios11/\">premios Bitácoras</a>. Estos premios que organiza la red de blogs <a href=\"http://bitacoras.com/\">Bitacoras.com</a> son unos galardones que tratan de reconocer el trabajo y el mérito de los bloggers de habla hispana.\r\n\r\nEste año hemos decidido participar en estos premios. Para votarnos tan solo tienes que hacer click en el banner que podrás encontrar de forma permanente en la barra lateral de dSong, o bajo este párrafo. Ahí deberás identificarte con tu cuenta de Twitter, de Facebook o de Bitacoras.com y finalmente enviarnos tu voto en la categoría de mejor blog cultural. Así mismo te animamos a que votes a tus blogs favoritos en el resto de categorías que puedes encontrar. Tenéis de plazo hasta el día 1 de Noviembre.\r\n<p style=\"text-align: center;\"><a href=\"http://bitacoras.com/premios11/votar/37972e8eba2f800670f15d5ce95cd6be912fac5f\"><img src=\"http://static2.bitacoras.com/images/premios/2011/botones/180x120.gif\" alt=\"Votar en los Premios Bitacoras.com\" border=\"0\" /></a></p>\r\nSi te gusta dSong desde aquí pedimos tu voto. Te estaremos muy agradecidos ;-)",
  "author": {
    "name": "admin",
    "url": "http://dsong.es/",
    "gravatar_url": "https://s.gravatar.com/avatar/fd76fad1a29311d18a4f0a17dff6eef2"
  },
  "comments": [

  ],
  "metadata": {
    "category": "Noticias"
  }
}
